MANIFEST.in
README.rst
setup.py
traits_enaml/__init__.py
traits_enaml/compat.py
traits_enaml/trait_operators.py
traits_enaml/traits_tracer.py
traits_enaml/utils.py
traits_enaml.egg-info/PKG-INFO
traits_enaml.egg-info/SOURCES.txt
traits_enaml.egg-info/dependency_links.txt
traits_enaml.egg-info/requires.txt
traits_enaml.egg-info/top_level.txt
traits_enaml/testing/__init__.py
traits_enaml/testing/atom_test_assistant.py
traits_enaml/testing/enaml_test_assistant.py
traits_enaml/testing/event_loop_helper.py
traits_enaml/testing/gui_test_assistant.py
traits_enaml/testing/tests/__init__.py
traits_enaml/testing/tests/enaml_test_container.enaml
traits_enaml/testing/tests/test_atom_test_assistant.py
traits_enaml/testing/tests/test_enaml_test_assistant.py
traits_enaml/testing/tests/test_gui_test_assistant.py
traits_enaml/tests/__init__.py
traits_enaml/tests/test_autoview.py
traits_enaml/tests/test_enable_canvas.py
traits_enaml/tests/test_gl_canvas.py
traits_enaml/tests/test_mayavi_canvas.py
traits_enaml/tests/test_trait_operators.py
traits_enaml/tests/test_traits_view.py
traits_enaml/tests/test_traits_view_dynamic.py
traits_enaml/tests/test_utils.py
traits_enaml/widgets/__init__.py
traits_enaml/widgets/auto_editors.enaml
traits_enaml/widgets/auto_view.py
traits_enaml/widgets/enable_canvas.py
traits_enaml/widgets/gl_canvas.py
traits_enaml/widgets/mayavi_canvas.py
traits_enaml/widgets/traits_view.py