Metadata-Version: 2.1
Name: traits-enaml
Version: 0.3.0
Summary: Utilities for interoperation between Traits and Enaml
Home-page: https://github.com/enthought/traits-enaml
Author: Enthought, Inc
Author-email: info@enthought.com
License: UNKNOWN
Platform: UNKNOWN
Provides-Extra: enable
Provides-Extra: mayavi
Provides-Extra: opengl
